{
  "Records": [
    {
      "EventSource": "aws:sns",
      "EventVersion": "1.0",
      "EventSubscriptionArn": "arn:aws:sns:us-east-1:123456789012:IncomingEmail:12345678",
      "Sns": {
          "Type": "Notification",
          "MessageId": "EXAMPLE7c191be45-e9aedb9a-02f9-4d12-a87d-dd0099a07f8a-000000",
          "TopicArn": "arn:aws:sns:us-east-1:123456789012:IncomingEmail",
          "Subject": "Amazon SES Email Receipt Notification",
          "Message": {
            "notificationType": "Received",
            "mail": {
              "timestamp": "2019-09-06T18:52:14.965Z",
              "source": "0100016d07eb7477-8e1938ce-475e-4e4b-89cb-example-000000@amazonses.com",
              "messageId": "12345678901example",
              "destination": ["recipient@example.com"],
              "headersTruncated": false,
              "headers": [{
                "name": "Return-Path",
                "value": "<0100016d07eb7477-8e1938ce-475e-4e4b-89cb-example-000000@amazonses.com>"
              }, {
                "name": "Received",
                "value": "from a1-23.smtp-out.amazonses.com (a1-23.smtp-out.amazonses.com [203.0.113.0]) byinbound-smtp.us-east-1.amazonaws.com with SMTP id12345678901example for recipient@example.com; Fri, 06 Sep 201918:52:14 +0000 (UTC)"
              }, {
                "name": "X-SES-Spam-Verdict",
                "value": "PASS"
              }, {
                "name": "X-SES-Virus-Verdict",
                "value": "PASS"
              }, {
                "name": "Received-SPF",
                "value": "pass (spfCheck: domain of amazonses.com designates 203.0.113.0 as permitted sender)client-ip=203.0.113.0; envelope-from=0100016d07eb7477-8e1938ce-475e-4e4b-89cb-example-000000@amazonses.com; helo=a1-23.smtp-out.amazonses.com;"
              }, {
                "name": "Authentication-Results",
                "value": "amazonses.com; spf=pass (spfCheck: domain of amazonses.com designates 203.0.113.0as permitted sender) client-ip=203.0.113.0; envelope-from=0100016d07eb7477-8e1938ce-475e-4e4b-89cb-example-000000@amazonses.com; helo=a1-23.smtp-out.amazonses.com;dkim=pass header.i=@amazonses.com; dmarc=none header.from=example.com;"
              }, {
                "name": "X-SES-RECEIPT",
                "value": "AEFBQUFBQUFBQUFFQkx0QUJZZENEXAMPLE="
              }, {
                "name": "X-SES-DKIM-SIGNATURE",
                "value": "a=rsa-sha256; q=dns/txt; b=d5azwgA2iBqAjA4NBm1ARzjJ95raRmy4G84iVdd3x2JzSHeUnQuTuLmJAqRrYY3WpMIVRFy01hITaguCVjUPWBR0xF6fCEXH85cf3RNeFQyLfWZqoXKfBdjFRV+13troDterH2MxBUL8rjzcvdHetl0ImwlaK2PGmePTexample=; c=relaxed/simple; s=EXAMPLE7c191be45-e9aedb9a-02f9-4d12-a87d-dd0099a07f8a-000000; d=amazonses.com; t=1567795935; v=1; bh=CZ1SghsYaA6SSCbitzsLISeFoNlpdtH1Pyiexample=; h=From:To:Cc:Bcc:Subject:Date:Message-ID:MIME-Version:Content-Type:X-SES-RECEIPT;"
              }, {
                "name": "DKIM-Signature",
                "value": "v=1; a=rsa-sha256; q=dns/txt; c=relaxed/simple; s=EXAMPLE7c191be45-e9aedb9a-02f9-4d12-a87d-dd0099a07f8a-000000; d=amazonses.com; t=1567795934; h=From:To:Subject:MIME-Version:Content-Type:Message-ID:Date:Feedback-ID; bh=CZ1SghsYaA6SSCbitzsLISeFoNlpdtH1Pyiexample=; b=L6VXqR1PSN/FYqJI/VAfPRKFgtakcHCYJvuJqVYbuJT8I3FOhqOvkbcgHxOgswoxPfvGrL6S53H8Er5Do/CPvOM4Tx3ilE+a0GTYVLjKmwltNeN09YWlJAoqG5KMQPZUxRYaNvYPInLzUdGirdjkbSIgZEnrvq5MzaMWexample="
              }, {
                "name": "From",
                "value": "sender@example.com"
              }, {
                "name": "To",
                "value": "recipient@example.com"
              }, {
                "name": "Subject",
                "value": "Amazon SES Test"
              }, {
                "name": "MIME-Version",
                "value": "1.0"
              }, {
                "name": "Content-Type",
                "value": "multipart/alternative;  boundary=\"----=_Part_869787_396523212.15677example\""
              }, {
                "name": "Message-ID",
                "value": "<0100016d07eb7477-8e1938ce-475e-4e4b-89cb-example-000000@email.amazonses.com>"
              }, {
                "name": "Date",
                "value": "Fri, 6 Sep 2019 18:52:14 +0000"
              }, {
                "name": "X-SES-Outgoing",
                "value": "2019.09.06-203.0.113.0"
              }, {
                "name": "Feedback-ID",
                "value": "1.us-east-1.ZitRoTk0xziun8WEJevt+cSJ17QNuCwulg2D2v3nrT0=:AmazonSES"
              }],
              "commonHeaders": {
                "returnPath": "0100016d07eb7477-8e1938ce-475e-4e4b-89cb-example-000000@amazonses.com",
                "from": ["sender@example.com"],
                "date": "Fri, 6 Sep 2019 18:52:14 +0000",
                "to": ["recipient@example.com"],
                "messageId": "<0100016d07eb7477-8e1938ce-475e-4e4b-89cb-example-000000@email.amazonses.com>",
                "subject": "Amazon SES Test"
              }
            },
            "receipt": {
              "timestamp": "2019-09-06T18:52:14.965Z",
              "processingTimeMillis": 1098,
              "recipients": ["recipient@example.com"],
              "spamVerdict": {
                "status": "PASS"
              },
              "virusVerdict": {
                "status": "PASS"
              },
              "spfVerdict": {
                "status": "PASS"
              },
              "dkimVerdict": {
                "status": "GRAY"
              },
              "dmarcVerdict": {
                "status": "GRAY"
              },
              "action": {
                "type": "SNS",
                "topicArn": "arn:aws:sns:us-east-1:123456789012:IncomingEmail",
                "encoding": "BASE64"
              }
            },
            "content": "Return-Path: <lsaric@extensionengine.com>\nReceived: from mail-ed1-f41.google.com (mail-ed1-f41.google.com [209.85.208.41])\n by inbound-smtp.us-east-1.amazonaws.com with SMTP id aeoa6jnrmgn26pbkbjg96ua0gtj2s6n9jtoe5n01\n for info@pbz.extnsn.com;\n Wed, 23 Sep 2020 13:47:49 +0000 (UTC)\nX-SES-Spam-Verdict: PASS\nX-SES-Virus-Verdict: PASS\nReceived-SPF: pass (spfCheck: domain of extensionengine.com designates 209.85.208.41 as permitted sender) client-ip=209.85.208.41; envelope-from=lsaric@extensionengine.com; helo=mail-ed1-f41.google.com;\nAuthentication-Results: amazonses.com;\n spf=pass (spfCheck: domain of extensionengine.com designates 209.85.208.41 as permitted sender) client-ip=209.85.208.41; envelope-from=lsaric@extensionengine.com; helo=mail-ed1-f41.google.com;\n dkim=pass header.i=@extensionengine.com;\n dmarc=pass header.from=extensionengine.com;\nX-SES-RECEIPT: AEFBQUFBQUFBQUFGcGhWRzRURUtiWHFPdlNWa1RoMTlFaHVzQit1b3BCRGtzR2lJZWpjZThYbkJxREhIU2VlY1ZpczFNMFRNaXFrU1JSd0g3dWhHa3F6VTc5aHhYY3lDemwySEpvUkdvZFhmT3hDTXkzNnhFYll2bmF0SFVocjd6RkU3TFk5dytXWmRjby9NeDlLOG14YlRXNXQxUVRLQnNscXUyMVhabWFuRytOYUJFVEw3TzZkYk1iMy8vcUtVUkhIOElLZi9LV1VoUmdaVzFjTE54QlEvWHJMTng4b3lOZEJPMy96ZUVoOU91eXhQUHZvMHFXQW5lc2RaUjFqRUYvQSsrVXZhRWlJb0E2c2RseXJkODlZRVcyMXprZHZUVkxoOG45WUxTOHVJbmYwNkd0TE9sQVE9PQ==\nX-SES-DKIM-SIGNATURE: a=rsa-sha256; q=dns/txt; b=LYglfiCJbRU3Rj94n5UyiZrkhmvfoaE//k9WMveJBRNGsQnRqtA8Tq/9Wv9OJnubuQT1Qt6pmb4+qSoWfgzNNegYI8A0miA7izZw/iYbiwXpUWRp5zm/r1xI5NIBcMHMi3H+eNL+tkJ7KQd0rhSnpltp6Uspbi68whPxPLM/us0=; c=relaxed/simple; s=224i4yxa5dv7c2xz3womw6peuasteono; d=amazonses.com; t=1600868870; v=1; bh=T6movg3Ckfl9MQH++qvi4D3AHK6YJUAhszrV5grGGJw=; h=From:To:Cc:Bcc:Subject:Date:Message-ID:MIME-Version:Content-Type:X-SES-RECEIPT;\nReceived: by mail-ed1-f41.google.com with SMTP id l17so19887431edq.12\n        for <info@pbz.extnsn.com>; Wed, 23 Sep 2020 06:47:49 -0700 (PDT)\nDKIM-Signature: v=1; a=rsa-sha256; c=relaxed/relaxed;\n        d=extensionengine.com; s=google;\n        h=mime-version:from:date:message-id:subject:to;\n        bh=gRITSPF9f2hJ1XHNDSaSkLdXRSd99J9kZPvWjzME9pw=;\n        b=kGeZZnPvkFRzo0PTLVyeKbOQOPAgQ+LHKS+tkBs/9XjjtYttcixy9VBy11joaDPHi4\n         cowfbHSPGQkjfxkDBOneFek8QD7mKjbCRN/hU/LzXsl996dauj++TyThvGtjTXa8BAY9\n         EKLe3DDak4YoX5s7F6gTq7phtRihtGpLwovEEeHSEtwze1maPJps8EjkO0HiNnLdXIzM\n         yimxoPnz6uzNDtx602gykpmBOML7dieWXwHBm7/juCAwkQdJURySh+ry5OLAGDBDRRwJ\n         h3TpymL+u9yWjdJRNQa730ovN3z4d+2D0n5dHq6+y2SOV6D26Xu/zhJuPw8UlM95joZD\n         pfCQ==\nX-Google-DKIM-Signature: v=1; a=rsa-sha256; c=relaxed/relaxed;\n        d=1e100.net; s=20161025;\n        h=x-gm-message-state:mime-version:from:date:message-id:subject:to;\n        bh=gRITSPF9f2hJ1XHNDSaSkLdXRSd99J9kZPvWjzME9pw=;\n        b=RaFlyXATvrTUwjLz/am8yd4z08yYCEAP28JzStvYXiqUbBMMKCiJIVVsZPYio61bqg\n         95lAeVmTaUguUBVBCA9Q75SASuWHtqwvw2rswi//1961rFcszqLxx0siA6Hxz+VKhtVh\n         QAtKnx43H0qbF2u5j5cpJxu1MJpBssbJJTyQ23HhM+kxalc3aAWiYUAt8E4p6mqBtrBO\n         I+51Wd/tc46hGGzuVHp9fAUD9nB/Dqfas+wdqY5O+6xllBQ8arFevmr15Kz1dcfDWqkP\n         Ii8CkYaFkWA5sD24WD1KKJ000iKnLHXPjRd7OQOXQ0kMVJcDFFQkWxqi/KsN8bI1Csev\n         d9aA==\nX-Gm-Message-State: AOAM5302aHVyuI6jIKbE9oR4txWyGWtTKkQUWvv6WG4688yf9peJkynf\n\ty43qZihZg4mR1xk1BhpohP/BFIRwmbgkCXywdA7VlDwaqSib2A==\nX-Google-Smtp-Source: ABdhPJz2l78itMijFqMLcKoxraPKaqg5jX6VMXSIEbZqSDp2UnNZUjxV7ZvA4o99wm18sn0W8b4VB+/koJGx/Hju5wY=\nX-Received: by 2002:aa7:d4d4:: with SMTP id t20mr9831842edr.229.1600868868380;\n Wed, 23 Sep 2020 06:47:48 -0700 (PDT)\nMIME-Version: 1.0\nFrom: \"Saric, Luka\" <lsaric@extensionengine.com>\nDate: Wed, 23 Sep 2020 15:47:37 +0200\nMessage-ID: <CALnn1TWSUbhVK+eSpfrxChMNbcXNGsR9UyT642GgHCc34OD15Q@mail.gmail.com>\nSubject: Test_attach\nTo: info@pbz.extnsn.com\nContent-Type: multipart/mixed; boundary=\"0000000000003b8c4805affb54eb\"\n\n--0000000000003b8c4805affb54eb\nContent-Type: multipart/alternative; boundary=\"0000000000003b8c4705affb54e9\"\n\n--0000000000003b8c4705affb54e9\nContent-Type: text/plain; charset=\"UTF-8\"\n\nattachments\n\n--0000000000003b8c4705affb54e9\nContent-Type: text/html; charset=\"UTF-8\"\n\n<div dir=\"ltr\">attachments</div>\n\n--0000000000003b8c4705affb54e9--\n--0000000000003b8c4805affb54eb\nContent-Type: application/octet-stream; name=\"1110779471-20200818.rtf.sgn\"\nContent-Disposition: attachment; filename=\"1110779471-20200818.rtf.sgn\"\nContent-Transfer-Encoding: base64\nContent-ID: <f_kfffzb6k0>\nX-Attachment-Id: f_kfffzb6k0\n\nPD94bWwgdmVyc2lvbj0iMS4wIiA/Pg0KPCFET0NUWVBFIEZpbGVVcGxvYWQgU1lTVEVNICIiPg0K\nPEZpbGVVcGxvYWQ+DQo8VGltZVN0YW1wPg0KMjAyMDA4MTgyMzQzNTkNCjwvVGltZVN0YW1wPg0K\nPEZpbGUgY29tcHJlc3M9InppcCIgZW5jb2Rpbmc9ImJhc2U2NCI+DQo8IVtDREFUQVsNClVFc0RC\nQlFBQ0FBSUFIMjlFbEVBQUFBQUFBQUFBQUFBQUFBWEFBQUFNVEV4TURjM09UUTNNUzB5TURJd01E\nZ3hPQzV5ZEdibFYxMXUNCjAwQVFmcS9FSGVhUlZpWGRYVHV4blRlSGhHQmE3TWhPQzZyOHNvazN3\nWW16dGpaMmtJcTRBRWZvQThkQm5BVDFHSXpkRk9xb2Z3SEUNCmo1aEUzdEZveC92TjdQejVYYWp5\nQ1EyNVhNYlZZNXhOS1d1U01CS1RDWGtYVGxLWjU2TUVHUkpPRm1ra2xJU2pZaHhISEo2bWNwa20N\nCjR2MzduVERoTWxxT2VTYkNEQi9xRGFVV01TNzV0N1JsNm1RblhNWGk3VHlXRWEyNHN6a0xGMXhO\na3liUkswWmRNYm5acEJVelFnYVANClhkTG16c0IzVHZ4ZTE3V2hZN3VITnB6YWZiL1hnZnZKT1Qy\neHUvWWhERHo4QjBmZWlldTlCTi8rZk93ZXd5K2xJRmRjeG1QZUJucEENCkgrMmc2UW84cDlNR3dw\ncGFzMlVaaHNiVzR2cmluSzE0eE9jd1VnM1VKZHFEVCt6eXZGaEFqT3I1dkR6V2JCQ3p3UWdqRDMy\nQmR5YjUNCm5FTU01L0ZFY1ZqeHBNaEYrN2Jkei8xRG9CYXRnLzl6Rk9SY3pnUmtTdVJ2MGtpbTAr\nK2UyQ1RhWWczRDBQZU5LL0Erdnlna09qeWQNCnRkRXNuUUxUZEFLRVdCUW9KUVlZbG00QXZlblFW\nODZ6SVR6dU9FOTMyekRvblBhZisrejFOcWlQNTBVbVk0aUthYnJDTlZQcFF1UWcNCk9VUmMzdWg1\nc2svSUgvZjFHbldXWW94L3ZCOTJxM2tOZFprRFRDY01IYXNibFA1RzFHNjZTbUZaaFVuN25xMjBw\nVFYwZGkxQ1hINFcNCnJ6QXplS1RFa3NNOGlXZEM1aGhidmRmRG5oczRudHR6KzQ3YmcyN0R3OTgr\nQkVQZmUySDdBZFltUnZZeGo1SFdWYXFlTWY2b3VzbkwNCkVMeWJmREVSU3NneGh4R1hjM0ZuS21m\neEVyS0VmMEZyK1MxN1BsUlpMdmtDVFZtL3pGbWlUbDVYT0s1RTlaamJjTWZONVVnVlV3N3ENCkcr\nYWZwS0c0NExPNjZIRzNtQll6c1Z1VERhcWdMTVYxeUtVVmNTNlNHVC9JVkx6Z0ZidHh4aUF0emNJ\nd0xrdkJOWTBmaEh4WmtDL0wNCjZQWTV1d0htTnN4YmR3ZDFMakFtMW5pZS9GdTBSazBiNnc2a015\nd2xCcWFXeGpUQ0RJdG81b2JaWmY5akZ0WE1ab3NhOXpsOHBYaU8NClZXMnF4RGxtUkZFR3dCMVpW\ncjlTcCsvNTRIdjlJK2NUL0NWVUJ4all2djJpZDFKV3BHdGs2UFdlanQzdXV5K2ZVTk95ZmdMQWRp\nTkkNCnJVMWNYVjlaT0NFWUhEbER1SDBRd1MzVUpPWTJzODdEUVAvVFdiSzN0d2VIZU9mVnpEdkVh\nMGZCalJQbmY3TDhYWVRUSXVDOGVvRWYNClNqQlZSU2JBa1huWlRBTXVNNTRtNlJvMWZreDlCVkJM\nQndqdC9PYzdPQU1BQUpFTkFBQlFTd0VDRkFBVUFBZ0FDQUI5dlJKUjdmem4NCk96Z0RBQUNSRFFB\nQUZ3QUFBQUFBQUFBQUFBQUFBQUFBQUFBQU1URXhNRGMzT1RRM01TMHlNREl3TURneE9DNXlkR1pR\nU3dVR0FBQUENCkFBRUFBUUJGQUFBQWZRTUFBQUFBDQpdXT4NCjwvRmlsZT4NCjxTaWduZXI+DQo8\nQ2VydGlmaWNhdGU+DQozMDgyMDJGOTMwODIwMUUxQTAwMzAyMDEwMjAyMDQ0Q0FGMkY0NzMwMEQw\nNjA5MkE4NjQ4ODZGNzBEMDEwMTA1MDUwMDMwMkIzMTBCMzAwOTA2MDM1NTA0MDYxMzAyNDg1MjMx\nMEMzMDBBMDYwMzU1MDQwQTEzMDM1MDQyNUEzMTBFMzAwQzA2MDM1NTA0MDMxMzA1NTA0MjVBNDM0\nMTMwMUUxNzBEMzEzNzMwMzQzMjMwMzEzMjMyMzIzMTM0NUExNzBEMzEzOTMwMzQzMjMwMzEzMjMy\nMzIzMTM0NUEzMDc0MzEwQjMwMDkwNjAzNTUwNDA2MTMwMjQ4NTIzMTI0MzAyMjA2MDM1NTA0MEEx\nMzFCNTA3MjY5NzY3MjY1NjQ2RTYxMjA2MjYxNkU2QjYxMjA1QTYxNjc3MjY1NjIyMDY0MkU2NDJF\nMzExMzMwMTEwNjAzNTUwNDBCMTQwQTUwNDI1QTQzNEY0RDQwNEU0NTU0MzEyQTMwMjgwNjAzNTUw\nNDAzMTMyMTU1NzI2NTY0MjA3QTYxMjA2NTZDNjU2Qjc0NzI2RjZFNjk2MzZCNzUyMDZCNkY2RDc1\nNkU2OTZCNjE2MzY5NkE3NTMwODE5RjMwMEQwNjA5MkE4NjQ4ODZGNzBEMDEwMTAxMDUwMDAzODE4\nRDAwMzA4MTg5MDI4MTgxMDBBNjNGRjIzNkI1QzA3NkZCMTYyNTg3NjU5NkY0NDIxODRCRUE3MDVG\nODAzRTgwM0U3RUIwMDBDNzIxMDZFMkE2NDlDQTYwQjcxN0NGQzQxQjk3MUQ0RDFEOTJDQjhCNjUw\nMTlBNUI0OEYzMTg3OEVDMERBRjJGQkI0Mzg4QTNBMkNFRUZBNDIzMjlFQzMwNDE2NDBDQUM0QkRF\nQUQxNUQ0QzE0MEYwMEFEMzkxNUU1MkIzMjZFQ0UzNjI4MjM3MEE5NEE1NzAwQTczODFEQjA2ODI4\nNUM0MjNENUZCQkMwREI3Qzg2RjlCN0YxNkI2MzBCQzFDNUJEOEZFNDM2Q0YxMDIwMzAxMDAwMUEz\nNjAzMDVFMzAwOTA2MDM1NTFEMTMwNDAyMzAwMDMwMEIwNjAzNTUxRDBGMDQwNDAzMDIwMUZFMzA0\nNDA2MDM1NTFEMjMwNDNEMzAzQkExMzNBNDMxMzAyRjMxMEIzMDA5MDYwMzU1MDQwNjEzMDI0ODUy\nMzEwQzMwMEEwNjAzNTUwNDBBMTMwMzUwNDI1QTMxMTIzMDEwMDYwMzU1MDQwMzEzMDk1MDQyNUE1\nMjZGNkY3NDQzNDE4MjA0NEE1RTJBMTIzMDBEMDYwOTJBODY0ODg2RjcwRDAxMDEwNTA1MDAwMzgy\nMDEwMTAwNEVEQzdERUU3MkEyMTAzQzRDNDQ0OEE0QzkzQ0E4ODlCNTJCNTI5MkNEM0UxOEQyNTVD\nMjlERkRFQTZDMjRBRjVEOThDM0Q1OUM5MUEyMzQxM0Q2OEZDMjNFNTIyQ0M0OTM1QkVDMUU0Rjc4\nMDIwRTgxMDU0QTEwNERCNUU0NzE3MEEwOUUyNERGRkIwNkJDQjc1QzE1NUVBMTMyMENGODU5RTI4\nNTExN0RDNDIzMUE1MTE2QTZDNzJGNkNEMjExNENDMDk4M0RBMUIxM0UwNjZCMDM2QkJFNkU0NTA4\nNjMwQzhENTI5NUJDMjAyNzkxQUMwMzU2QkQxOUJCRDA5N0FCMDBGREM1REQ4QUUzQzU1MTJFQjY3\nMDk4OTBDM0RBOTFGQjI2OTY3OTc4QkM5Q0VFNkIyRkQxRUFBQjc3MzRCNjc0NDhDMzcxQTlGMkJG\nOTlGMjI4MjI5MDA2OEIxODczODEwMTIwOEZDQTQyM0M1MkVGMTFBM0MwRTcxRDlDQjc4NjVGOEQx\nNDMwMDQ3OEI2QkYwNEZEODBBQjE1QzQxN0NERkMxRjJDNDgzREZGNEQwNTM0Q0I0NzlDOTU1RjZF\nQ0Y3MDNBMTA3MUIwRTE5MjJFMzJERThENjdFN0RDQTg5RDc5QTBFQUJBRkEwN0U4QURDN0Q2QTJG\nOTY4MkENCjwvQ2VydGlmaWNhdGU+DQo8U2lnbj4NCjAzQ0E5QTlFMkRCMzc4RDhGRTQxRjU1RjMw\nMzZGMDQ1QjQzMzA3QzY5MkJGODlBQ0I4MkQzRUFGQUEyMzJEQjBFRDc1Q0RDQTMwMjdCMzEwOEIy\nRDJEQzYzOTczMTBFNjRGMDczMUQ2QTU4OEY1MUFCNjZCNDkzMTU0MTBDNzY3RThENUMwNjE3MTU1\nQkI0OTk3NDg0MjExRjJBQjk2OEFGQTQzQjVCMjA3QTFFRDFENDhFRjgzRTY5MTIwM0RBNTY3NDE4\nNENBN0Q1QUM0QjM0MDY2NDU5MjgwMzA4Nzc3MTIwQ0Q3QTVCRDI2NkREQURCOTMwNDQxRTFEOUYy\nNTMNCjwvU2lnbj4NCjxUaW1lPg0KMjAyMDA4MTgyMzQzNTkNCjwvVGltZT4NCjwvU2lnbmVyPg0K\nPC9GaWxlVXBsb2FkPg==\n--0000000000003b8c4805affb54eb\nContent-Type: application/octet-stream; \n\tname=\"DIZV_HR4123400091110779471_20200804.xml.sgn\"\nContent-Disposition: attachment; \n\tfilename=\"DIZV_HR4123400091110779471_20200804.xml.sgn\"\nContent-Transfer-Encoding: base64\nContent-ID: <f_kfffzb751>\nX-Attachment-Id: f_kfffzb751\n\nPD94bWwgdmVyc2lvbj0iMS4wIiA/Pg0KPCFET0NUWVBFIEZpbGVVcGxvYWQgU1lTVEVNICIiPg0K\nPEZpbGVVcGxvYWQ+DQo8VGltZVN0YW1wPg0KMjAyMDA4MDUwMTE4MzMNCjwvVGltZVN0YW1wPg0K\nPEZpbGUgY29tcHJlc3M9InppcCIgZW5jb2Rpbmc9ImJhc2U2NCI+DQo8IVtDREFUQVsNClVFc0RC\nQlFBQ0FBSUFGQUtCVkVBQUFBQUFBQUFBQUFBQUFBbkFBQUFSRWxhVmw5SVVqUXhNak0wTURBd09U\nRXhNVEEzTnprME56RmYNCk1qQXlNREE0TURRdWVHMXNoVlRiYnVJd0VIM25LN3c4czRsdFFpNG9U\nWlV1cU4xV2dncllWZFdxaWd4eFc2ZGdvOXk2eWhmdXAvUXoNCjFzNEZDS0F0dk1Senpwa1oyM1Bz\nWHY3WnJFRk80NFFKZnRGRkd1d0N5bGNpWlB6MW92dkJlQ2cra3U4SUQyRDMwdXU0MjJVUnNDSVgN\nCm9kY0J3QlZzNldFRFlvU2dZU0hrNmlxZ2dDMkpVeFlSRHhrMnhvYXJOMnVGY1ZLdzNITy9QZjBZ\nK1F2L2FmeXdHRS9tUDZlVDhlVDYNCjUyUU1SdHBVL3ArZlBWZXZtRXBEd3BnbXhKc3ZadE5iZnph\nLzh3R0dQWUNnL0lGSC8zbzJ2bkwxbXFQb3kxaEVWWnZFdzZhckg2NFYNCkhwSTAyelFCYUdqUTFq\nREUwTlZiZ0dLeUplSGV6Y3hBdUcvSVlnNlNXN1VzUis3VzFVdE1rWklQOXBKNjkxZVAxemN6L09E\ncTFWb2gNCk9WbG5LZG1mV0x1M29JVHBjWXROdU9MWEtYaTI4V3hEdG5pd2JoR1N0Y2k5WC9QUmps\nRUdLc28ycHVtYkNMa0lrcFR3aUhwb1lHZ0cNCjd2Y2NkVGZIWUtNUkc1b0duQVFoNFVHWXZZcWNN\neW5zYThocWhPY1k1OVJia2Nha2tDRHNRWGdzM0lHVmtvdDgzNlltNTY2VUhFWmINCjI2NXlWVEVa\naldrWXFLUDA1UDNzdm5jZ1dXV3kzcHFrTEtYclNJblpocFNmKzNrOGU5bmxPUDVQM3BRb1IvYXJF\ndWRIdnRPYTdrNDENCjFuc2ZmRkZZR1RPbUx6U1c1ajBvSlljU3lMQTJSQVBVZHpBMGpFR1pzazF2\na2lSNS9FWlVvWlU4NklNc2Q5bFd5SU1PU1VSQVNITlcNCkVOQzVtZDBCeDdRMUd3OTZ5T3FsOUpO\nRXdPejE1WTFCV05ZNHl0WVVlVit6aVBMMFhMZFhzVmFROTNXVWZYSzJva01Nb1EwTkFLRnANCjJx\naTZnMVB4N2dCa2V5dDJwdm43MlhUazMvcGdOUDZ0RGNGK2dJRTBTdzhzeG4vOTJ5RXdOZGw0ZFRK\nSGVacjgxZFB3emlOV1VCVS8NCmZUYjJXRnRUMi9sVWNPaHo5ZFlVWENTMWowVExhVzJremEvdEky\ncHZIUVVicnB5RGdJVzFXNGhuMlJiRURyVE12dWtneDlXUDRNcGgNCitvbkZkcUg2UWF2bXFGNzhB\nMUJMQndqZTd0TityUUlBQUVvR0FBQlFTd0VDRkFBVUFBZ0FDQUJRQ2dWUjN1N1RmcTBDQUFCS0Jn\nQUENCkp3QUFBQUFBQUFBQUFBQUFBQUFBQUFBQVJFbGFWbDlJVWpReE1qTTBNREF3T1RFeE1UQTNO\nemswTnpGZk1qQXlNREE0TURRdWVHMXMNClVFc0ZCZ0FBQUFBQkFBRUFWUUFBQUFJREFBQUFBQT09\nDQpdXT4NCjwvRmlsZT4NCjxTaWduZXI+DQo8Q2VydGlmaWNhdGU+DQozMDgyMDJGOTMwODIwMUUx\nQTAwMzAyMDEwMjAyMDQ0Q0FGMkY0NzMwMEQwNjA5MkE4NjQ4ODZGNzBEMDEwMTA1MDUwMDMwMkIz\nMTBCMzAwOTA2MDM1NTA0MDYxMzAyNDg1MjMxMEMzMDBBMDYwMzU1MDQwQTEzMDM1MDQyNUEzMTBF\nMzAwQzA2MDM1NTA0MDMxMzA1NTA0MjVBNDM0MTMwMUUxNzBEMzEzNzMwMzQzMjMwMzEzMjMyMzIz\nMTM0NUExNzBEMzEzOTMwMzQzMjMwMzEzMjMyMzIzMTM0NUEzMDc0MzEwQjMwMDkwNjAzNTUwNDA2\nMTMwMjQ4NTIzMTI0MzAyMjA2MDM1NTA0MEExMzFCNTA3MjY5NzY3MjY1NjQ2RTYxMjA2MjYxNkU2\nQjYxMjA1QTYxNjc3MjY1NjIyMDY0MkU2NDJFMzExMzMwMTEwNjAzNTUwNDBCMTQwQTUwNDI1QTQz\nNEY0RDQwNEU0NTU0MzEyQTMwMjgwNjAzNTUwNDAzMTMyMTU1NzI2NTY0MjA3QTYxMjA2NTZDNjU2\nQjc0NzI2RjZFNjk2MzZCNzUyMDZCNkY2RDc1NkU2OTZCNjE2MzY5NkE3NTMwODE5RjMwMEQwNjA5\nMkE4NjQ4ODZGNzBEMDEwMTAxMDUwMDAzODE4RDAwMzA4MTg5MDI4MTgxMDBBNjNGRjIzNkI1QzA3\nNkZCMTYyNTg3NjU5NkY0NDIxODRCRUE3MDVGODAzRTgwM0U3RUIwMDBDNzIxMDZFMkE2NDlDQTYw\nQjcxN0NGQzQxQjk3MUQ0RDFEOTJDQjhCNjUwMTlBNUI0OEYzMTg3OEVDMERBRjJGQkI0Mzg4QTNB\nMkNFRUZBNDIzMjlFQzMwNDE2NDBDQUM0QkRFQUQxNUQ0QzE0MEYwMEFEMzkxNUU1MkIzMjZFQ0Uz\nNjI4MjM3MEE5NEE1NzAwQTczODFEQjA2ODI4NUM0MjNENUZCQkMwREI3Qzg2RjlCN0YxNkI2MzBC\nQzFDNUJEOEZFNDM2Q0YxMDIwMzAxMDAwMUEzNjAzMDVFMzAwOTA2MDM1NTFEMTMwNDAyMzAwMDMw\nMEIwNjAzNTUxRDBGMDQwNDAzMDIwMUZFMzA0NDA2MDM1NTFEMjMwNDNEMzAzQkExMzNBNDMxMzAy\nRjMxMEIzMDA5MDYwMzU1MDQwNjEzMDI0ODUyMzEwQzMwMEEwNjAzNTUwNDBBMTMwMzUwNDI1QTMx\nMTIzMDEwMDYwMzU1MDQwMzEzMDk1MDQyNUE1MjZGNkY3NDQzNDE4MjA0NEE1RTJBMTIzMDBEMDYw\nOTJBODY0ODg2RjcwRDAxMDEwNTA1MDAwMzgyMDEwMTAwNEVEQzdERUU3MkEyMTAzQzRDNDQ0OEE0\nQzkzQ0E4ODlCNTJCNTI5MkNEM0UxOEQyNTVDMjlERkRFQTZDMjRBRjVEOThDM0Q1OUM5MUEyMzQx\nM0Q2OEZDMjNFNTIyQ0M0OTM1QkVDMUU0Rjc4MDIwRTgxMDU0QTEwNERCNUU0NzE3MEEwOUUyNERG\nRkIwNkJDQjc1QzE1NUVBMTMyMENGODU5RTI4NTExN0RDNDIzMUE1MTE2QTZDNzJGNkNEMjExNEND\nMDk4M0RBMUIxM0UwNjZCMDM2QkJFNkU0NTA4NjMwQzhENTI5NUJDMjAyNzkxQUMwMzU2QkQxOUJC\nRDA5N0FCMDBGREM1REQ4QUUzQzU1MTJFQjY3MDk4OTBDM0RBOTFGQjI2OTY3OTc4QkM5Q0VFNkIy\nRkQxRUFBQjc3MzRCNjc0NDhDMzcxQTlGMkJGOTlGMjI4MjI5MDA2OEIxODczODEwMTIwOEZDQTQy\nM0M1MkVGMTFBM0MwRTcxRDlDQjc4NjVGOEQxNDMwMDQ3OEI2QkYwNEZEODBBQjE1QzQxN0NERkMx\nRjJDNDgzREZGNEQwNTM0Q0I0NzlDOTU1RjZFQ0Y3MDNBMTA3MUIwRTE5MjJFMzJERThENjdFN0RD\nQTg5RDc5QTBFQUJBRkEwN0U4QURDN0Q2QTJGOTY4MkENCjwvQ2VydGlmaWNhdGU+DQo8U2lnbj4N\nCjAwQkY3REE4QUY4MzY3REVEQTk1MkIxMjVGQjk2NjcxMkU3NDVGOTdCNTQ3REZGODgyQjZFNTY5\nRDMzNzA4QTk4Rjk2OTZBRTZEQ0RFQzkyOEE5RDA1ODY1RkZFRTFGMjRFNEEyRUJBQ0FENTU0NTQz\nNjA4Qzk3OEFGQTlGMENDRDI3QjY1ODU0RTM5NjYwQzE3QzNCRjVFQTFENjY4N0JEQTZFNEU4RTZF\nRjk3OEQyMzM2REZFMEFFMUJBMDkwRkM0RDdDNDMxM0ZCMUJDM0EyMkNDMDYyRUFCOEQzMkQwMkRF\nODAyRjRGNDcwNEQyQjQwQzkzMTIxMTE3QTdCOUYNCjwvU2lnbj4NCjxUaW1lPg0KMjAyMDA4MDUw\nMTE4MzMNCjwvVGltZT4NCjwvU2lnbmVyPg0KPC9GaWxlVXBsb2FkPg==\n--0000000000003b8c4805affb54eb--\n"
          },
          "Timestamp": "2019-09-06T18:52:16.076Z",
          "SignatureVersion": "1",
          "Signature": "012345678901example==",
          "SigningCertUrl": "https://sns.us-east-1.amazonaws.com/SimpleNotificationService-01234567890123456789012345678901.pem",
          "UnsubscribeUrl": "https://sns.us-east-1.amazonaws.com/?Action=Unsubscribe&SubscriptionArn=arn:aws:sns:us-east-1:0123456789012:IncomingEmail:0b863538-3f32-462e-9c89-8d8e0example",
          "MessageAttributes": {}
      }
    }
  ]
}
